{"bones":[{"name":"root"},{"name":"bone1","parent":"root","x":-0.5,"y":57,"scaleX":0.286,"scaleY":0.286},{"name":"bone1-copy","parent":"root","x":-0.5,"y":57,"scaleX":0.286,"scaleY":0.286}],"slots":[{"name":"rayo","bone":"bone1","color":"ffffff5d","attachment":"rayo"},{"name":"rayo-copy","bone":"bone1-copy","attachment":"rayo"}],"skins":{"default":{"rayo":{"rayo":{"width":166,"height":245}},"rayo-copy":{"rayo":{"width":166,"height":245}}}},"animations":{"floating":{"bones":{"bone1":{"translate":[{"time":0,"x":0,"y":0},{"time":1,"x":0,"y":5},{"time":2,"x":0,"y":0}]},"bone1-copy":{"translate":[{"time":0,"x":0,"y":0},{"time":1,"x":0,"y":5},{"time":2,"x":0,"y":0}],"scale":[{"time":0,"x":0.999,"y":0.999},{"time":1,"x":1.04,"y":1.04},{"time":2,"x":0.991,"y":0.991}]}},"slots":{"rayo":{"color":[{"time":0,"color":"ffffff5d"},{"time":1,"color":"fffbf4ff"},{"time":2,"color":"fbffffff"}]},"rayo-copy":{"color":[{"time":0,"color":"ffffffff"},{"time":1,"color":"f9ffedfa"},{"time":2,"color":"fefffe00"}]}}}}}